Workbook

Sheet challenge_report_2022_10-2025-1
A1: Organization name | B1: Hackathon name | C1: Hackathon url | D1: Hackathon published date | E1: Total participant count | F1: Total valid submissions (excluding spam) | G1: In person vs virtual | H1: Column 1 | I1: Column 2
A2: BrickHack | B2: BrickHack X | C2: https://brickhack-x.devpost.com | D2: 2024-02-12 12:19:49 -0500 | E2: 176 | F2: 53 | G2: College/ University | H2: =VALUE(LEFT(D2,4)) -> 2024
A3: Minnetonka High School | B3: TonkaHacks 2022 | C3: https://tonkahacks.devpost.com | D3: 2022-11-12 15:33:51 -0500 | E3: 37 | F3: 18 | G3: High School | H3: =VALUE(LEFT(D3,4)) -> 2022
A4: Protocol Labs | B4: Protocol Labs (Filecoin Green)-Sustainable Blockchain Hackathon | C4: https://sbsboston.devpost.com | D4: 2023-02-01 16:37:29 -0500 | E4: 427 | F4: 39 | G4: Private Sector | H4: =VALUE(LEFT(D4,4)) -> 2023
A5: Women in Computer Science | B5: HopperHacks 2023 | C5: https://hopperhacks-2023.devpost.com | D5: 2023-01-30 15:18:33 -0500 | E5: 127 | F5: 24 | G5: College/ University | H5: =VALUE(LEFT(D5,4)) -> 2023
A6: ACM Hack | B6: Hack Internal | C6: https://lairtxhtoh.devpost.com | D6: 2023-03-04 13:16:41 -0500 | E6: 4 | F6: 0 | G6: College/ University | H6: =VALUE(LEFT(D6,4)) -> 2023
A7: MegaHackathonLeague | B7: MegaHack<>Kinetik Challenge | C7: https://megahackkinetik.devpost.com | D7: 2024-10-25 19:11:41 -0400 | E7: 32 | F7: 16 | G7: Civic | H7: =VALUE(LEFT(D7,4)) -> 2024
A8: Society of Computer Developers | B8: WayneHacks | C8: https://waynehacks.devpost.com | D8: 2023-02-25 23:42:11 -0500 | E8: 50 | F8: 16 | G8: College/ University | H8: =VALUE(LEFT(D8,4)) -> 2023
A9: Humane Interface Design Enterprise | B9: Winter WonderHack 2023 | C9: https://winter-wonderhack-2023.devpost.com | D9: 2023-03-15 16:27:45 -0400 | E9: 8 | F9: 4 | G9: College/ University | H9: =VALUE(LEFT(D9,4)) -> 2023
A10: iata | B10: IATA ONE Record Hackathon – hosted by Lufthansa Cargo | C10: https://onerecord-fra.devpost.com | D10: 2022-12-06 05:11:46 -0500 | E10: 215 | F10: 20 | G10: Private Sector | H10: =VALUE(LEFT(D10,4)) -> 2022
A11: Rock Ridge High School | B11: Phoenix Hacks | C11: https://phoenix-hacks.devpost.com | D11: 2022-12-03 10:16:19 -0500 | E11: 72 | F11: 23 | G11: High School | H11: =VALUE(LEFT(D11,4)) -> 2022
A12: Brandeis University | B12: DeisHacks 2023 | C12: https://deishacks-2023.devpost.com | D12: 2023-02-03 14:43:38 -0500 | E12: 117 | F12: 33 | G12: College/ University | H12: =VALUE(LEFT(D12,4)) -> 2023
A13: Sahyadri Open Source Community | B13: Hacknight 2023 | C13: https://hacknight-23.devpost.com | D13: 2023-10-13 11:05:33 -0400 | E13: 336 | F13: 30 | G13: College/ University | H13: =VALUE(LEFT(D13,4)) -> 2023
... A24: Spartan Hackers | B24: Code Green | C24: https://code-green.devpost.com | D24: 2022-10-07 11:48:33 -0400 | E24: 121 | F24: 10 | G24: College/ University | H24: =VALUE(LEFT(D24,4)) -> 2022
A25: Hack the North | B25: Hack the North 2024 | C25: https://hackthenorth2024.devpost.com | D25: 2024-08-30 13:01:47 -0400 | E25: 835 | F25: 235 | H25: =VALUE(LEFT(D25,4)) -> 2024
A26: Hack the North | B26: Hack the North 2025 | C26: https://hackthenorth2025.devpost.com | D26: 2025-09-04 00:22:10 -0400 | E26: 873 | F26: 261 | H26: =VALUE(LEFT(D26,4)) -> 2025
A27: Minnetronix | B27: IoT Hack Day 2022 | C27: https://iot-hack-day-2022.devpost.com | D27: 2022-10-17 20:31:50 -0400 | E27: 4 | F27: 0 | G27: Civic | H27: =VALUE(LEFT(D27,4)) -> 2022
A28: Sego Lily Hacks | B28: Sego Lily Hacks | C28: https://sego-lily-hacks-2022.devpost.com | D28: 2022-10-01 22:56:17 -0400 | E28: 72 | F28: 16 | H28: =VALUE(LEFT(D28,4)) -> 2022
A29: Iroquois Ridge High School | B29: Hack The Ridge 2022 | C29: https://hack-the-ridge-2022.devpost.com | D29: 2022-12-09 23:26:36 -0500 | E29: 69 | F29: 26 | G29: High School | H29: =VALUE(LEFT(D29,4)) -> 2022
A30: Wellesley CS Club | B30: WHACK 2022 | C30: https://whack-2022.devpost.com | D30: 2022-11-08 09:48:26 -0500 | E30: 89 | F30: 24 | G30: College/ University | H30: =VALUE(LEFT(D30,4)) -> 2022
A31: Brook Codes | B31: Brook Codes 2022 | C31: https://brook-codes-2022.devpost.com | D31: 2022-10-02 17:24:36 -0400 | E31: 122 | F31: 44 | G31: High School | H31: =VALUE(LEFT(D31,4)) -> 2022
A32: TAMU Datathon | B32: TAMU Datathon 2022 | C32: https://tamudatathon2022.devpost.com | D32: 2022-10-02 20:20:49 -0400 | E32: 219 | F32: 75 | G32: College/ University | H32: =VALUE(LEFT(D32,4)) -> 2022
A33: HackAlphaX | B33: NextStep Hacks 2024 | C33: https://nextstep2024.devpost.com | D33: 2023-10-11 22:13:10 -0400 | E33: 403 | F33: 32 | G33: High School | H33: =VALUE(LEFT(D33,4)) -> 2023
A34: Global DevSlam | B34: FutureHack | C34: https://futurehack.devpost.com | D34: 2022-10-03 10:52:53 -0400 | E34: 141 | F34: 26 | G34: Private Sector | H34: =VALUE(LEFT(D34,4)) -> 2022
A35: ultra.io | B35: Ultra Uniq NFT PFP Hackathon | C35: https://ultrauniqhackathon.devpost.com | D35: 2022-10-03 07:06:22 -0400 | E35: 178 | F35: 41 | H35: =VALUE(LEFT(D35,4)) -> 2022
A36: M&T Bank | B36: Meet & Hack 2 | C36: https://meet-hack-2.devpost.com | D36: 2022-11-07 13:36:35 -0500 | E36: 64 | F36: 19 | G36: College/ University | H36: =VALUE(LEFT(D36,4)) -> 2022
A37: CCAD | B37: Hack@Davidson I | C37: https://hackdavidson.devpost.com | D37: 2022-10-18 18:09:54 -0400 | E37: 65 | F37: 12 | G37: College/ University | H37: =VALUE(LEFT(D37,4)) -> 2022
A38: Ohio University Entrepreneurship Club | B38: HackPalachia 2023 | C38: https://hackpalachiaou.devpost.com | D38: 2023-03-03 16:38:43 -0500 | E38: 32 | F38: 14 | G38: College/ University | H38: =VALUE(LEFT(D38,4)) -> 2023
A39: VandyHacks | B39: VandyHacks IX | C39: https://vandyhacks-ix.devpost.com | D39: 2022-10-21 13:29:21 -0400 | E39: 121 | F39: 35 | G39: College/ University | H39: =VALUE(LEFT(D39,4)) -> 2022
A40: SingleStore | B40: SingleStore Database Hackathon | C40: https://singlestore.devpost.com | D40: 2022-10-03 10:00:02 -0400 | E40: 536 | F40: 42 | H40: =VALUE(LEFT(D40,4)) -> 2022
A41: NUS High School | B41: NUSH HACK 2022 | C41: https://nushhack2022.devpost.com | D41: 2022-11-09 08:28:04 -0500 | E41: 22 | F41: 11 | G41: High School | H41: =VALUE(LEFT(D41,4)) -> 2022
A42: Treasure Hacks | B42: Treasure Hacks 3.0 | C42: https://treasure-hacks-3-0.devpost.com | D42: 2022-10-05 20:02:42 -0400 | E42: 573 | F42: 80 | G42: College/ University | H42: =VALUE(LEFT(D42,4)) -> 2022
A43: City of Syracuse | B43: Syracuse Open Data Day | C43: https://syracuse-open-data-day.devpost.com | D43: 2023-10-04 10:33:55 -0400 | E43: 52 | F43: 8 | G43: Civic | H43: =VALUE(LEFT(D43,4)) -> 2023
A44: Business Meets Tech @WHU | B44: BusinessMeetsTech IdeaHack! 2022 | C44: https://bmt-ideahack-2022.devpost.com | D44: 2022-10-04 14:15:19 -0400 | E44: 3 | F44: 1 | G44: College/ University | H44: =VALUE(LEFT(D44,4)) -> 2022
A45: zappar | B45: ZappARthon | C45: https://zapparthon.devpost.com | D45: 2022-11-08 12:40:38 -0500 | E45: 434 | F45: 34 | G45: Private Sector | H45: =VALUE(LEFT(D45,4)) -> 2022
A46: XDC Network | B46: XDC DeFi Hackathon | C46: https://xdc.devpost.com | D46: 2022-10-07 11:24:48 -0400 | E46: 473 | F46: 40 | H46: =VALUE(LEFT(D46,4)) -> 2022
A47: Mizzou Computing Association | B47: TigerHacks 2022 | C47: https://th22.devpost.com | D47: 2022-10-23 20:24:50 -0400 | E47: 312 | F47: 80 | G47: College/ University | H47: =VALUE(LEFT(D47,4)) -> 2022
A48: Amazon | B48: AWS Data Exchange for APIs Challenge | C48: https://awsdataexchange4apis.devpost.com | D48: 2022-10-10 10:00:25 -0400 | E48: 726 | F48: 30 | H48: =VALUE(LEFT(D48,4)) -> 2022
A49: BigRed//Hacks | B49: Cornell BigRed//Hacks 2022 | C49: https://bigred-hacks-2022.devpost.com | D49: 2022-10-13 00:36:56 -0400 | E49: 204 | F49: 57 | G49: College/ University | H49: =VALUE(LEFT(D49,4)) -> 2022
A50: Open Web Academy | B50: Open Web House Puerto Vallarta | C50: https://open-web-house.devpost.com | D50: 2022-10-25 19:22:04 -0400 | E50: 54 | F50: 5 | G50: Civic | H50: =VALUE(LEFT(D50,4)) -> 2022
A51: ACM UTSA | B51: Rowdy Datathon 2022 | C51: https://rowdydatathon2022.devpost.com | D51: 2022-10-01 22:59:13 -0400 | E51: 36 | F51: 10 | G51: College/ University | H51: =VALUE(LEFT(D51,4)) -> 2022
A52: Engine-4 | B52: Web3 Hackathon Puerto Rico 2.0 | C52: https://web3-hackathon-pr-2-0.devpost.com | D52: 2022-11-08 23:42:58 -0500 | E52: 43 | F52: 9 | H52: =VALUE(LEFT(D52,4)) -> 2022
A53: HackPSU | B53: HackPSU Fall 2022 | C53: https://hackpsu-fall-2022.devpost.com | D53: 2022-11-03 15:46:53 -0400 | E53: 115 | F53: 28 | G53: College/ University | H53: =VALUE(LEFT(D53,4)) -> 2022
A54: Bitcoin Association | B54: Zero-Knowledge Proof Hackathon | C54: https://bsvhackathon2022.devpost.com | D54: 2022-10-03 04:02:14 -0400 | E54: 913 | F54: 10 | G54: Private Sector | H54: =VALUE(LEFT(D54,4)) -> 2022
A55: Freetail Hackers | B55: HackTX 2022 | C55: https://hacktx-2022.devpost.com | D55: 2022-10-03 20:13:51 -0400 | E55: 386 | F55: 119 | G55: College/ University | H55: =VALUE(LEFT(D55,4)) -> 2022
A56: Jacobs University Bremen | B56: jacobsHack!2022 | C56: https://jacobshack-2022.devpost.com | D56: 2022-10-30 10:35:06 -0400 | E56: 99 | F56: 26 | G56: College/ University | H56: =VALUE(LEFT(D56,4)) -> 2022
A57: Courier | B57: Courier Hacks: Open Source | C57: https://courier-hacks-open-source.devpost.com | D57: 2022-10-02 00:43:52 -0400 | E57: 139 | F57: 21 | G57: Civic | H57: =VALUE(LEFT(D57,4)) -> 2022
A58: CAPATEC | B58: ETH Panama Hackathon 2022 | C58: https://eth-panama-hackathon.devpost.com | D58: 2022-10-14 12:00:29 -0400 | E58: 36 | F58: 11 | G58: Private Sector | H58: =VALUE(LEFT(D58,4)) -> 2022
A59: Featurepreneur | B59: Big Data Boss - Season 5 | C59: https://big-data-boss-season-5.devpost.com | D59: 2022-10-22 09:56:35 -0400 | E59: 22 | F59: 0 | G59: College/ University | H59: =VALUE(LEFT(D59,4)) -> 2022
A60: Code Kevudah | B60: Code Kevudah Hackathon | C60: https://code-kevudah-hackathon.devpost.com | D60: 2022-11-10 20:36:06 -0500 | E60: 23 | F60: 9 | G60: Civic | H60: =VALUE(LEFT(D60,4)) -> 2022
A61: HackHarvard | B61: HackHarvard 2022: Control, Alt, Create | C61: https://hackharvard2022.devpost.com | D61: 2022-10-08 13:59:54 -0400 | E61: 476 | F61: 125 | G61: College/ University | H61: =VALUE(LEFT(D61,4)) -> 2022
A62: hackUMBC | B62: hackUMBC Fall 2022 | C62: https://hackumbc-fall-2022.devpost.com | D62: 2022-10-01 13:07:57 -0400 | E62: 186 | F62: 57 | G62: College/ University | H62: =VALUE(LEFT(D62,4)) -> 2022
A63: TIE | B63: TIEU-MOCK | C63: https://tieu-mock2023.devpost.com | D63: 2022-10-01 10:21:19 -0400 | E63: 8 | F63: 5 | G63: College/ University | H63: =VALUE(LEFT(D63,4)) -> 2022
A64: GDSC USYD | B64: GDSC Game Jam | C64: https://gdsc-game-jam-2022.devpost.com | D64: 2022-10-01 19:36:10 -0400 | E64: 35 | F64: 11 | G64: College/ University | H64: =VALUE(LEFT(D64,4)) -> 2022
... A73: Edinburgh Hoppers | B73: Ada Hack 2022 | C73: https://ada-hack-2022.devpost.com | D73: 2022-10-14 09:12:41 -0400 | E73: 59 | F73: 19 | G73: College/ University | H73: =VALUE(LEFT(D73,4)) -> 2022
A74: hackhw | B74: HackHW 2022 | C74: https://hackhw-22.devpost.com | D74: 2022-10-05 14:01:57 -0400 | E74: 3 | F74: 1 | H74: =VALUE(LEFT(D74,4)) -> 2022
A75: HackDuke | B75: HackDuke: Code for Good 2022 | C75: https://hackduke-code-for-good-2022.devpost.com | D75: 2022-10-05 15:11:28 -0400 | E75: 174 | F75: 35 | G75: College/ University | H75: =VALUE(LEFT(D75,4)) -> 2022
A76: Major League Hacking | B76: RoboHacks 2 | C76: https://robohacks2.devpost.com | D76: 2022-10-05 16:44:49 -0400 | E76: 26 | F76: 10 | H76: =VALUE(LEFT(D76,4)) -> 2022
A77: Major League Hacking | B77: Hack And Snack | C77: https://hackandsnack.devpost.com | D77: 2022-10-06 13:51:07 -0400 | E77: 76 | F77: 17 | H77: =VALUE(LEFT(D77,4)) -> 2022
A78: Vivid Hacks | B78: Vivid Hacks RICI | C78: https://vivid-hacks-rici.devpost.com | D78: 2022-10-05 20:58:03 -0400 | E78: 74 | F78: 2 | H78: =VALUE(LEFT(D78,4)) -> 2022
A79: SF Go Club | B79: Hack the Game of GO | C79: https://hack-the-game-of-go.devpost.com | D79: 2022-10-06 01:14:27 -0400 | E79: 3 | F79: 0 | G79: Private Sector | H79: =VALUE(LEFT(D79,4)) -> 2022
A80: Lynbrook Engineering Club | B80: LEC Hacks 2.0 | C80: https://lec-hackathon.devpost.com | D80: 2022-11-06 00:59:03 -0400 | E80: 22 | F80: 3 | G80: High School | H80: =VALUE(LEFT(D80,4)) -> 2022
A81: TUM | B81: ML4Earth Hackathon 2022 (online) | C81: https://ml4earth.devpost.com | D81: 2022-11-04 04:07:35 -0400 | E81: 105 | F81: 9 | G81: College/ University | H81: =VALUE(LEFT(D81,4)) -> 2022
A82: Campus Code | B82: Campus Hack | C82: https://campushack1.devpost.com | D82: 2022-10-06 18:01:27 -0400 | E82: 106 | F82: 19 | G82: College/ University | H82: =VALUE(LEFT(D82,4)) -> 2022
A83: Germantown Friends School | B83: GFS Quackathon 2023 | C83: https://gfs-quackathon-2023.devpost.com | D83: 2022-11-22 11:37:36 -0500 | E83: 44 | F83: 11 | G83: High School | H83: =VALUE(LEFT(D83,4)) -> 2022
A84: Northern Illinois University | B84: 2022 FOOD SYSTEMS CHALLENGE HACK | C84: https://huskiehack22.devpost.com | D84: 2022-10-27 10:17:23 -0400 | E84: 35 | F84: 11 | G84: College/ University | H84: =VALUE(LEFT(D84,4)) -> 2022
A85: Microsoft | B85: Microsoft Azure Innovation Challenge | C85: https://health-innovationchallenge.devpost.com | D85: 2022-10-25 14:47:43 -0400 | E85: 356 | F85: 7 | H85: =VALUE(LEFT(D85,4)) -> 2022
A86: TechTogether | B86: TechTogether New York 2023 | C86: https://techtogether-new-york-2023.devpost.com | D86: 2022-10-06 20:02:46 -0400 | E86: 21 | F86: 0 | G86: College/ University | H86: =VALUE(LEFT(D86,4)) -> 2022
A87: IEEE uOttawa Student Branch | B87: Hack the Hill | C87: https://hack-the-hill.devpost.com | D87: 2023-03-03 19:19:52 -0500 | E87: 195 | F87: 53 | G87: College/ University | H87: =VALUE(LEFT(D87,4)) -> 2023
A88: KAUST | B88: The Second SAAI Factory Hackathon | C88: https://saai2.devpost.com | D88: 2022-11-13 10:30:16 -0500 | E88: 331 | F88: 15 | G88: College/ University | H88: =VALUE(LEFT(D88,4)) -> 2022
A89: Chainlink Labs | B89: Chainlink Fall 2022 Hackathon | C89: https://chainlinkfall2022.devpost.com | D89: 2022-10-19 23:44:12 -0400 | E89: 1207 | F89: 373 | H89: =VALUE(LEFT(D89,4)) -> 2022
A90: Major League Hacking | B90: Pursuit 8.3 & 8.4 | C90: https://pursuit-8-3-8-4.devpost.com | D90: 2022-10-28 17:04:47 -0400 | E90: 40 | F90: 8 | G90: Private Sector | H90: =VALUE(LEFT(D90,4)) -> 2022
A91: TeenTechSF | B91: TeenTechSF 2022 Civic Hackathon | C91: https://2022-civic-hackathon.devpost.com | D91: 2022-10-07 21:26:15 -0400 | E91: 63 | F91: 16 | G91: High School | H91: =VALUE(LEFT(D91,4)) -> 2022
A92: Cal Hacks | B92: Cal Hacks 9.0 | C92: https://calhacks90.devpost.com | D92: 2022-10-14 19:50:49 -0400 | E92: 787 | F92: 211 | G92: College/ University | H92: =VALUE(LEFT(D92,4)) -> 2022
A93: Opportunity Hack | B93: Opportunity Hack 2022 | C93: https://opportunity-hack-2022.devpost.com | D93: 2022-10-08 22:28:31 -0400 | E93: 115 | F93: 3 | G93: Civic | H93: =VALUE(LEFT(D93,4)) -> 2022
A94: Web3 Devs Poland | B94: [Hybrid] HackOnChain | C94: https://hackonchain.devpost.com | D94: 2022-10-17 10:29:08 -0400 | E94: 104 | F94: 20 | H94: =VALUE(LEFT(D94,4)) -> 2022
A95: BostonHacks | B95: BostonHacks 2022 | C95: https://bostonhacks-2022.devpost.com | D95: 2022-10-31 19:13:09 -0400 | E95: 170 | F95: 45 | G95: College/ University | H95: =VALUE(LEFT(D95,4)) -> 2022
A96: DandyHacks Organizing Team | B96: DandyHacks'22 | C96: https://dandyhacks-2022.devpost.com | D96: 2022-10-09 16:16:16 -0400 | E96: 86 | F96: 28 | G96: College/ University | H96: =VALUE(LEFT(D96,4)) -> 2022
A97: Major League Hacking | B97: Global Hack Week October | C97: https://ghw-october.devpost.com | D97: 2022-10-10 11:06:04 -0400 | E97: 79 | F97: 6 | H97: =VALUE(LEFT(D97,4)) -> 2022
A98: Spark2Code | B98: Spark2Code SpreadLOVE - Join Discord ASAP! | C98: https://spark2code-spreadlove.devpost.com | D98: 2022-10-11 12:03:31 -0400 | E98: 101 | F98: 18 | G98: High School | H98: =VALUE(LEFT(D98,4)) -> 2022
A99: Associació d'Estudiants de Dades | B99: Datathon FME 2022 | C99: https://datathon-fme.devpost.com | D99: 2022-10-10 14:10:35 -0400 | E99: 298 | F99: 22 | G99: College/ University | H99: =VALUE(LEFT(D99,4)) -> 2022
A100: University of Pittsburgh | B100: Pitt Challenge 2022 | C100: https://pittchallenge2022.devpost.com | D100: 2022-10-13 20:34:21 -0400 | E100: 77 | F100: 24 | G100: College/ University | H100: =VALUE(LEFT(D100,4)) -> 2022
A101: ACM UMN | B101: MinneHack 2023 | C101: https://minnehack-2023.devpost.com | D101: 2023-01-28 14:04:33 -0500 | E101: 164 | F101: 43 | G101: College/ University | H101: =VALUE(LEFT(D101,4)) -> 2023
A102: AWS User Group India | B102: AWSomeify Hackathon | C102: https://awsomeify.devpost.com | D102: 2022-10-19 23:19:17 -0400 | E102: 380 | F102: 38 | G102: Civic | H102: =VALUE(LEFT(D102,4)) -> 2022
A103: Slim.AI | B103: Slimplicity: Slim.AI Hackathon | C103: https://slim-ai-hackathon.devpost.com | D103: 2022-10-17 10:20:29 -0400 | E103: 408 | F103: 11 | G103: Civic | H103: =VALUE(LEFT(D103,4)) -> 2022
A104: HudsonAlpha Institute for Biotechnology | B104: (HATCH) HudsonAlpha Tech Challenge 2023 | C104: https://tech-challenge-2023.devpost.com | D104: 2022-10-12 13:40:54 -0400 | E104: 97 | F104: 13 | G104: Private Sector | H104: =VALUE(LEFT(D104,4)) -> 2022
A105: SacHacks | B105: SacHacks IV | C105: https://sachacks-iv.devpost.com | D105: 2022-10-15 21:27:42 -0400 | E105: 137 | F105: 52 | G105: College/ University | H105: =VALUE(LEFT(D105,4)) -> 2022
A106: Major League Hacking | B106: BeagleHacks | C106: https://beaglehacks.devpost.com | D106: 2022-10-13 09:06:58 -0400 | E106: 35 | F106: 9 | H106: =VALUE(LEFT(D106,4)) -> 2022
A107: Bitcoin Bay | B107: BlockHack Global FE 2022 | C107: https://blockhack-global-fe-2022.devpost.com | D107: 2022-10-17 13:23:49 -0400 | E107: 267 | F107: 12 | G107: College/ University | H107: =VALUE(LEFT(D107,4)) -> 2022
A108: Royal Holloway Computing Society | B108: Royal Hackaway v6 | C108: https://royal-hackaway-v6.devpost.com | D108: 2022-11-09 11:26:46 -0500 | E108: 173 | F108: 39 | G108: College/ University | H108: =VALUE(LEFT(D108,4)) -> 2022
A109: WeCanCode | B109: MLH Coding Challenge | C109: https://mlh-coding-challenge.devpost.com | D109: 2022-10-13 12:09:47 -0400 | E109: 15 | F109: 4 | G109: Civic | H109: =VALUE(LEFT(D109,4)) -> 2022
A110: Major League Hacking | B110: YeeHaw Hacks 2 | C110: https://yeehaw-hacks-2.devpost.com | D110: 2022-10-13 14:24:24 -0400 | E110: 66 | F110: 15 | H110: =VALUE(LEFT(D110,4)) -> 2022
A111: ieee uoft | B111: NewHacks 2022 | C111: https://newhacks-2022.devpost.com | D111: 2022-10-19 19:24:03 -0400 | E111: 215 | F111: 45 | G111: College/ University | H111: =VALUE(LEFT(D111,4)) -> 2022
A112: Major League Hacking | B112: Hack or Treat 2 | C112: https://hack-or-treat-2.devpost.com | D112: 2022-10-20 08:26:21 -0400 | E112: 51 | F112: 13 | H112: =VALUE(LEFT(D112,4)) -> 2022
A113: SportsKPI | B113: Haryana Steelers Hackathon | C113: https://haryanasteelers.devpost.com | D113: 2022-10-20 23:07:51 -0400 | E113: 34 | F113: 3 | G113: Civic | H113: =VALUE(LEFT(D113,4)) -> 2022
A114: Trekk & 3D | B114: Metaverse Hackathon | C114: https://uplift-hackaverse.devpost.com | D114: 2022-10-16 13:20:32 -0400 | E114: 10 | F114: 0 | G114: Private Sector | H114: =VALUE(LEFT(D114,4)) -> 2022
A115: MegaHackathonLeague | B115: MEGA Hackathon 2023 | C115: https://mega-hackathon-2023.devpost.com | D115: 2023-02-28 18:51:28 -0500 | E115: 409 | F115: 67 | G115: Civic | H115: =VALUE(LEFT(D115,4)) -> 2023
A116: Roche | B116: Dementia - Our Common Challenge | C116: https://dementia-our-common-challenge.devpost.com | D116: 2022-10-16 10:35:14 -0400 | E116: 24 | F116: 3 | G116: Private Sector | H116: =VALUE(LEFT(D116,4)) -> 2022
A117: HackNC | B117: HackNC 2022 | C117: https://hacknc-2022.devpost.com | D117: 2022-10-28 11:08:58 -0400 | E117: 266 | F117: 67 | G117: College/ University | H117: =VALUE(LEFT(D117,4)) -> 2022
A118: DubHacks | B118: DubHacks '22 | C118: https://dubhacks-22.devpost.com | D118: 2022-10-18 17:18:04 -0400 | E118: 453 | F118: 134 | G118: College/ University | H118: =VALUE(LEFT(D118,4)) -> 2022
...

Sheet Sheet3
A1: Year | B1: Total Hackathons | C1: Total Participants | D1: Avg Participants | E1: Total Valid Submissions | F1: Avg Valid Submissions | G1: YoY Growth (%)
A2: 2022 | B2: =COUNTIF('challenge_report_2022_10-2025-1'!H:H, A2) -> 294 | C2: =SUMIF('challenge_report_2022_10-2025-1'!H:H, A2, 'challenge_report_2022_10-2025-1'!E:E) -> 46388 | D2: =AVERAGEIF('challenge_report_2022_10-2025-1'!H:H, A2, 'challenge_report_2022_10-2025-1'!E:E) -> 157.78231 | E2: =SUMIF('challenge_report_2022_10-2025-1'!H:H, A2, 'challenge_report_2022_10-2025-1'!F:F) -> 8135 | F2: =AVERAGEIF('challenge_report_2022_10-2025-1'!H:H, A2, 'challenge_report_2022_10-2025-1'!F:F) -> 27.670068 | G2: -%
A3: 2023 | B3: =COUNTIF('challenge_report_2022_10-2025-1'!H:H, A3) -> 1266 | C3: =SUMIF('challenge_report_2022_10-2025-1'!H:H, A3, 'challenge_report_2022_10-2025-1'!E:E) -> 225143 | D3: =AVERAGEIF('challenge_report_2022_10-2025-1'!H:H, A3, 'challenge_report_2022_10-2025-1'!E:E) -> 177.83807 | E3: =SUMIF('challenge_report_2022_10-2025-1'!H:H, A3, 'challenge_report_2022_10-2025-1'!F:F) -> 37683 | F3: =AVERAGEIF('challenge_report_2022_10-2025-1'!H:H, A3, 'challenge_report_2022_10-2025-1'!F:F) -> 29.765403 | G3: =IF(A3>MIN($A$2:$A$10), (C3 - OFFSET(C3, -1, 0)) / OFFSET(C3, -1, 0), "") -> 3.853475
A4: 2024 | B4: =COUNTIF('challenge_report_2022_10-2025-1'!H:H, A4) -> 1376 | C4: =SUMIF('challenge_report_2022_10-2025-1'!H:H, A4, 'challenge_report_2022_10-2025-1'!E:E) -> 324326 | D4: =AVERAGEIF('challenge_report_2022_10-2025-1'!H:H, A4, 'challenge_report_2022_10-2025-1'!E:E) -> 235.70203 | E4: =SUMIF('challenge_report_2022_10-2025-1'!H:H, A4, 'challenge_report_2022_10-2025-1'!F:F) -> 47509 | F4: =AVERAGEIF('challenge_report_2022_10-2025-1'!H:H, A4, 'challenge_report_2022_10-2025-1'!F:F) -> 34.52689 | G4: =IF(A4>MIN($A$2:$A$10), (C4 - OFFSET(C4, -1, 0)) / OFFSET(C4, -1, 0), "") -> 0.44053335
A5: 2025 | B5: =COUNTIF('challenge_report_2022_10-2025-1'!H:H, A5) -> 1546 | C5: =SUMIF('challenge_report_2022_10-2025-1'!H:H, A5, 'challenge_report_2022_10-2025-1'!E:E) -> 542578 | D5: =AVERAGEIF('challenge_report_2022_10-2025-1'!H:H, A5, 'challenge_report_2022_10-2025-1'!E:E) -> 350.95602 | E5: =SUMIF('challenge_report_2022_10-2025-1'!H:H, A5, 'challenge_report_2022_10-2025-1'!F:F) -> 66502 | F5: =AVERAGEIF('challenge_report_2022_10-2025-1'!H:H, A5, 'challenge_report_2022_10-2025-1'!F:F) -> 43.015524 | G5: =IF(A5>MIN($A$2:$A$10), (C5 - OFFSET(C5, -1, 0)) / OFFSET(C5, -1, 0), "") -> 0.67294019

Sheet Key Accounts 2025
A1: name | B1: Hackathon name | C1: Hackathon url | D1: Total participant count | E1: Hackathon published date | F1: Total valid submissions | G1: In person vs virtual
A2: Atlassian | B2: Forge Quest: Bonus Level | C2: https://forgequest.devpost.com | D2: 2371 | E2: 2025-05-20 12:09:25 -0400 | F2: 283
A3: Atlassian | B3: Codegeist 2025: Atlassian Williams Racing Edition | C3: https://codegeistxawr.devpost.com | D3: 750 | E3: 2025-10-08 12:19:52 -0400 | F3: 6 | G3: Ongoing
A4: AWS | B4: AWS AI Agent Global Hackathon | C4: https://aws-agent-hackathon.devpost.com | D4: 9558 | E4: 2025-09-08 14:59:17 -0400 | F4: 610
A5: Amazon | B5: AWS Presents: Breaking Barriers Virtual Challenge | C5: https://aws-breaking-barriers.devpost.com | D5: 2336 | E5: 2025-04-21 14:32:09 -0400 | F5: 102
A6: Amazon | B6: AWS Lambda Hackathon | C6: https://awslambdahackathon.devpost.com | D6: 3725 | E6: 2025-06-03 11:39:22 -0400 | F6: 331
A7: Kiro | B7: Code with Kiro Hackathon | C7: https://kiro.devpost.com | D7: 10012 | E7: 2025-07-14 08:59:42 -0400 | F7: 552
A8: AWS Hong Kong | B8: AWS AI Hackathon Hong Kong | C8: https://aws-hong-kong-hackathon.devpost.com | D8: 841 | E8: 2025-08-15 00:20:33 -0400 | F8: 129
A9: Amazon | B9: Rift Rewind Hackathon | C9: https://riftrewind.devpost.com | D9: 2268 | E9: 2025-09-15 12:03:45 -0400 | F9: 5 | G9: Ongoing
A10: AWS & NVIDIA | B10: Agentic AI Unleashed: AWS & NVIDIA Hackathon | C10: https://nvidia-aws.devpost.com | D10: 1861 | E10: 2025-09-29 11:01:35 -0400 | F10: 10 | G10: Ongoing
A11: Google | B11: Agent Development Kit Hackathon with Google Cloud | C11: https://googlecloudmultiagents.devpost.com | D11: 10397 | E11: 2025-04-09 11:00:28 -0400 | F11: 476
A12: Google | B12: GKE Turns 10 Hackathon | C12: https://gketurns10.devpost.com | D12: 4759 | E12: 2025-08-04 10:49:58 -0400 | F12: 133
A13: Google | B13: AI in Action | C13: https://ai-in-action.devpost.com | D13: 6729 | E13: 2025-04-09 10:30:34 -0400 | F13: 295
A14: Google | B14: Google Maps Platform Awards | C14: https://googlemapsplatformawards.devpost.com | D14: 3951 | E14: 2025-05-20 11:55:20 -0400 | F14: 416
A15: Google | B15: Baseline Tooling Hackathon | C15: https://baseline.devpost.com | D15: 2962 | E15: 2025-09-02 11:56:46 -0400 | F15: 172
A16: Google | B16: AI Accelerate: Unlocking New Frontiers | C16: https://ai-accelerate.devpost.com | D16: 2792 | E16: 2025-09-16 11:59:59 -0400 | F16: 171
A17: Google | B17: Google Chrome Built-in AI Challenge 2025 | C17: https://googlechromeai2025.devpost.com | D17: 13821 | E17: 2025-09-09 11:50:20 -0400 | F17: 564 | G17: ongoing
A18: Google | B18: Cloud Run Hackathon | C18: https://run.devpost.com | D18: 2250 | E18: 2025-10-06 11:54:30 -0400 | F18: 24 | G18: Ongoing
A19: Meta | B19: Meta Horizon Creator Competition: Mobile Genre Showdown | C19: https://mhcp-mobile-genre-competition.devpost.com | D19: 1551 | E19: 2025-03-11 13:29:02 -0400 | F19: 281
A20: Meta | B20: Meta Horizon Creator Competition: Elevate Your Mobile World | C20: https://mhcp-mobile-update-competition.devpost.com | D20: 1414 | E20: 2025-06-20 12:54:35 -0400 | F20: 185
A21: Meta | B21: Meta Horizon Creator Competition: Open Source Champions | C21: https://mhcp-open-source-competition.devpost.com | D21: 1233 | E21: 2025-08-14 12:46:35 -0400 | F21: 329
A22: Meta | B22: Meta Horizon Creator Competition: Mobile Genre Showdown - Reloaded | C22: https://mhcp-mobile-genre-2.devpost.com | D22: 1598 | E22: 2025-09-18 17:03:25 -0400 | F22: 83
A23: Salesforce | B23: Agentforce Virtual Hackathon | C23: https://agentforcehackathon.devpost.com | D23: 7235 | E23: 2025-03-04 14:04:48 -0500 | F23: 225
A24: Tableau | B24: Tableau Next Virtual Hackathon | C24: https://tableau.devpost.com | D24: 4531 | E24: 2025-07-24 12:23:07 -0400 | F24: 99
D25: =SUM(D2:D24) -> 98945

Sheet Overview
A1: Here's a summary of the categories and their distribution: • College/University: This category represents the largest portion, with 2,162 hackathons (54.13%). • High School: High schools hosted 952 hackathons, accounting for 23.84% of the total. • Private Sector: The private sector organized 616 hackathons, making up 15.42% of the events. • Civic: Civic organizations hosted 264 hackathons, which is 6.61% of the total.
